kidsui/__init__.py
kidsui-0.2.0.dist-info/METADATA
kidsui-0.2.0.dist-info/WHEEL
kidsui-0.2.0.dist-info/top_level.txt
kidsui-0.2.0.dist-info/RECORD
