Metadata-Version: 2.4
Name: kidsui
Version: 0.2.0
Summary: A colorful GUI library for kids built on Kivy
Home-page: https://github.com/yourusername/kidsui
Author: Ahmed Mohammed
Author-email: programmer2020dev@gmail.com
Classifier: Programming Language :: Python :: 3
Classifier: Intended Audience :: Education
Classifier: License :: OSI Approved :: MIT License
Classifier: Operating System :: OS Independent
Requires-Python: >=3.7
Requires-Dist: kivy
Dynamic: author
Dynamic: author-email
Dynamic: classifier
Dynamic: description
Dynamic: description-content-type
Dynamic: home-page
Dynamic: requires-dist
Dynamic: requires-python
Dynamic: summary
